Workbook

Sheet P&L & Profit Integration
A1: COMPREHENSIVE COST ANALYSIS & PROFIT INTEGRATION MODEL
A2: Automated Gross-to-Net Profit Bridge with Real-Time Manual Expense Aggregation
A9: 1. PROFIT & LOSS BREAKDOWN (STATEMENT VIEW)
A11: Line Item | B11: Current Period ($) | C11: % of Revenue | D11: Benchmark % | E11: Variance / Notes | F11: Calculation Formula / Reference
A12: Gross Sales / Invoiced Revenue | B12: 1250000 | C12: =B12/B$12 | D12: 100.0% | E12: Total billed clients across all accounts | F12: Base Topline Revenue
A13: Direct Cost of Goods Sold (COGS) | B13: 475000 | C13: =B13/B$12 | D13: 38.0% | E13: Direct hardware, parts, supplier costs | F13: Direct Cost
A14: Direct Labor & Field Subcontractors | B14: 185000 | C14: =B14/B$12 | D14: 14.8% | E14: Installation & field commissioning wages | F14: Direct Cost
A15: GROSS PROFIT | B15: =B12-B13-B14 | C15: =B15/B$12 | D15: 47.2% | E15: Core gross margin generated by projects | F15: =Revenue - COGS - Direct Labor
A16: Gross Margin % | B16: =B15/B12 | C16: - | D16: 45.0% - 50.0% | E16: Target gross margin threshold is >= 45% | F16: =Gross Profit / Revenue
A18: MANUALLY LOGGED OPERATING EXPENSES | B18: ='Manual Expense Entry'!F4 | C18: =B18/B$12 | D18: 22.5% | E18: Live feed from manual entry ledger | F18: =SUM('Manual Expense Entry'!D8:D100)
A19: - Operating Costs | B19: =SUMIFS('Manual Expense Entry'!D$8:D$100, 'Manual Expense Entry'!C$8:C$100, "Operating Costs") | C19: =B19/B$12 | D19: 3.0% | E19: Facility & daily operational overhead | F19: =SUMIFS(ledger, category, "Operating Costs")
A20: - Salaries & Wages (Overhead) | B20: =SUMIFS('Manual Expense Entry'!D$8:D$100, 'Manual Expense Entry'!C$8:C$100, "Salaries & Wages") | C20: =B20/B$12 | D20: 8.0% | E20: Admin, sales & executive payroll | F20: =SUMIFS(ledger, category, "Salaries & Wages")
A21: - Utilities & Facilities | B21: =SUMIFS('Manual Expense Entry'!D$8:D$100, 'Manual Expense Entry'!C$8:C$100, "Utilities & Facilities") | C21: =B21/B$12 | D21: 1.5% | E21: Electricity, water, office rent, internet | F21: =SUMIFS(ledger, category, "Utilities & Facilities")
A22: - Marketing & Advertising | B22: =SUMIFS('Manual Expense Entry'!D$8:D$100, 'Manual Expense Entry'!C$8:C$100, "Marketing & Advertising") | C22: =B22/B$12 | D22: 2.5% | E22: Digital ads, exhibitions, branding campaigns | F22: =SUMIFS(ledger, category, "Marketing & Advertising")
A23: - Equipment & Maintenance | B23: =SUMIFS('Manual Expense Entry'!D$8:D$100, 'Manual Expense Entry'!C$8:C$100, "Equipment & Maintenance") | C23: =B23/B$12 | D23: 1.5% | E23: Tool repairs, fleet service, software subs | F23: =SUMIFS(ledger, category, "Equipment & Maintenance")
A24: - Shipping & Logistics | B24: =SUMIFS('Manual Expense Entry'!D$8:D$100, 'Manual Expense Entry'!C$8:C$100, "Shipping & Logistics") | C24: =B24/B$12 | D24: 1.2% | E24: Freight, courier, customs clearance fees | F24: =SUMIFS(ledger, category, "Shipping & Logistics")
A25: - Taxes & Compliance | B25: =SUMIFS('Manual Expense Entry'!D$8:D$100, 'Manual Expense Entry'!C$8:C$100, "Taxes & Compliance") | C25: =B25/B$12 | D25: 1.8% | E25: Municipal taxes, licensing fees, audit | F25: =SUMIFS(ledger, category, "Taxes & Compliance")
A26: - Professional Services | B26: =SUMIFS('Manual Expense Entry'!D$8:D$100, 'Manual Expense Entry'!C$8:C$100, "Professional Services") | C26: =B26/B$12 | D26: 1.0% | E26: External legal advisory, CPA retainers | F26: =SUMIFS(ledger, category, "Professional Services")
A27: - Depreciation & Amortization | B27: =SUMIFS('Manual Expense Entry'!D$8:D$100, 'Manual Expense Entry'!C$8:C$100, "Depreciation") | C27: =B27/B$12 | D27: 1.0% | E27: Machinery & tech equipment depreciation | F27: =SUMIFS(ledger, category, "Depreciation")
A28: - Miscellaneous / Other / Custom | B28: =SUMIFS('Manual Expense Entry'!D$8:D$100, 'Manual Expense Entry'!C$8:C$100, "Miscellaneous / Other") + SUMIFS('Manual Expense Entry'!D$8:D$100, 'Manual Expense Entry'!C$8:C$100, "Custom / Project-Specific") | C28: =B28/B$12 | D28: 1.0% | E28: Sundry & ad-hoc project expenses | F28: =SUMIFS(ledger, category, other/custom)
A30: NET OPERATING PROFIT (EBIT) | B30: =B15-B18 | C30: =B30/B$12 | D30: 24.7% | E30: Healthy net operating profitability | F30: =Gross Profit - Total Manual Expenses
A31: Net Profit Margin % | B31: =B30/B12 | C31: - | D31: 20.0% - 25.0% | E31: Target net margin threshold >= 20% | F31: =Net Operating Profit / Revenue

Sheet Manual Expense Entry
A1: DEDICATED MANUAL EXPENSE ENTRY LEDGER
A2: Insert new expense rows below. Category dropdowns, running totals, and P&L deductions update dynamically.
A4: TOTAL EXPENSES LOGGED: | B4: =F4 | D4: RECORD COUNT: | E4: =COUNTA(B8:B100) | F4: =SUM(D8:D100)
A7: Entry ID | B7: Date (YYYY-MM-DD) | C7: Expense Category | D7: Amount ($) | E7: Running Total ($) | F7: Vendor / Payee & Reference | G7: Business Purpose / Notes
A8: EXP-001 | B8: 2025-01-05 | C8: Operating Costs | D8: 14500 | E8: =SUM(D$8:D8) | F8: SmartHQ Facility Mgmt | G8: Headquarters floor lease & janitorial services
A9: EXP-002 | B9: 2025-01-08 | C9: Salaries & Wages | D9: 48000 | E9: =SUM(D$8:D9) | F9: Payroll Clearing Account | G9: Monthly administrative, sales & management payroll
A10: EXP-003 | B10: 2025-01-10 | C10: Utilities & Facilities | D10: 6800 | E10: =SUM(D$8:D10) | F10: City Power & Fiber Telecom | G10: Electricity, high-speed fiber backbone, water
A11: EXP-004 | B11: 2025-01-12 | C11: Marketing & Advertising | D11: 12400 | E11: =SUM(D$8:D11) | F11: Google & LinkedIn Ads | G11: Q1 smart home commercial lead generation campaigns
A12: EXP-005 | B12: 2025-01-15 | C12: Equipment & Maintenance | D12: 8200 | E12: =SUM(D$8:D12) | F12: TechPro Calibration Ltd | G12: Testing gear calibration, technician fleet maintenance
A13: EXP-006 | B13: 2025-01-18 | C13: Shipping & Logistics | D13: 5900 | E13: =SUM(D$8:D13) | F13: Global Express Freight | G13: Air freight express for expedited microcontroller parts
A14: EXP-007 | B14: 2025-01-20 | C14: Taxes & Compliance | D14: 9500 | E14: =SUM(D$8:D14) | F14: Regulatory Authority | G14: Annual smart equipment compliance & safety certification
A15: EXP-008 | B15: 2025-01-22 | C15: Professional Services | D15: 6500 | E15: =SUM(D$8:D15) | F15: Apex Legal & CPA Partners | G15: Corporate legal retainer, quarterly financial audit
A16: EXP-009 | B16: 2025-01-25 | C16: Depreciation | D16: 4200 | E16: =SUM(D$8:D16) | F16: Internal Asset Schedule | G16: Monthly depreciation on laboratory and demo showroom gear
A17: EXP-010 | B17: 2025-01-28 | C17: Miscellaneous / Other | D17: 3100 | E17: =SUM(D$8:D17) | F17: Various Suppliers | G17: Staff training, technical library subscriptions, petty cash
A18: EXP-011 | B18: 2025-02-02 | C18: Custom / Project-Specific | D18: 5800 | E18: =SUM(D$8:D18) | F18: KNX Certification Center | G18: Advanced KNX Partner training for 2 automation engineers
A19: EXP-012 | B19: 2025-02-05 | C19: Operating Costs | D19: 11200 | E19: =SUM(D$8:D19) | F19: SmartHQ Storage Hub | G19: Offsite bonded warehouse rental for bulk switch inventory
A20: EXP-013 | E20: =IF(D20>0, SUM(D$8:D20), "")
A21: EXP-014 | E21: =IF(D21>0, SUM(D$8:D21), "")
A22: EXP-015 | E22: =IF(D22>0, SUM(D$8:D22), "")
A23: EXP-016 | E23: =IF(D23>0, SUM(D$8:D23), "")
A24: EXP-017 | E24: =IF(D24>0, SUM(D$8:D24), "")
A25: EXP-018 | E25: =IF(D25>0, SUM(D$8:D25), "")
A26: EXP-019 | E26: =IF(D26>0, SUM(D$8:D26), "")
A27: EXP-020 | E27: =IF(D27>0, SUM(D$8:D27), "")
A28: EXP-021 | E28: =IF(D28>0, SUM(D$8:D28), "")
A29: EXP-022 | E29: =IF(D29>0, SUM(D$8:D29), "")

Sheet Category Setup & Legend
A1: PREDEFINED EXPENSE CATEGORIES & METRIC LEGEND
A2: Master category definitions, accounting classification, target budgets, and real-time variance monitoring.
A7: Category Name | B7: Accounting Classification | C7: Cost Nature | D7: Monthly Budget Cap ($) | E7: Actual YTD Spend ($) | F7: Variance ($) | G7: Definition & Scope of Allowable Costs
A8: Operating Costs | B8: General & Administrative | C8: Semi-Variable | D8: 25000 | E8: =SUMIFS('Manual Expense Entry'!D$8:D$100, 'Manual Expense Entry'!C$8:C$100, A8) | F8: =D8-E8 | G8: General facility overhead, office lease, shared building charges, daily administration
A9: Salaries & Wages | B9: Personnel / Payroll | C9: Fixed | D9: 55000 | E9: =SUMIFS('Manual Expense Entry'!D$8:D$100, 'Manual Expense Entry'!C$8:C$100, A9) | F9: =D9-E9 | G9: Non-project staff salaries, management, sales commissions, administrative payroll & bonuses
A10: Utilities & Facilities | B10: Facility Overhead | C10: Fixed / Variable | D10: 8500 | E10: =SUMIFS('Manual Expense Entry'!D$8:D$100, 'Manual Expense Entry'!C$8:C$100, A10) | F10: =D10-E10 | G10: Electricity, municipal water, high-speed fiber internet, security, HVAC maintenance
A11: Marketing & Advertising | B11: Sales & Marketing | C11: Discretionary | D11: 15000 | E11: =SUMIFS('Manual Expense Entry'!D$8:D$100, 'Manual Expense Entry'!C$8:C$100, A11) | F11: =D11-E11 | G11: Digital PPC campaigns, showroom promotions, collateral printing, trade show presence
A12: Equipment & Maintenance | B12: Operations & Fleet | C12: Semi-Variable | D12: 10000 | E12: =SUMIFS('Manual Expense Entry'!D$8:D$100, 'Manual Expense Entry'!C$8:C$100, A12) | F12: =D12-E12 | G12: Testing & calibration tool upkeep, diagnostic software licenses, field technician vehicle service
A13: Shipping & Logistics | B13: Logistics Overhead | C13: Variable | D13: 7500 | E13: =SUMIFS('Manual Expense Entry'!D$8:D$100, 'Manual Expense Entry'!C$8:C$100, A13) | F13: =D13-E13 | G13: Freight inbound/outbound, courier delivery, express customs clearance, packaging supplies
A14: Taxes & Compliance | B14: Statutory & Compliance | C14: Fixed / Mandatory | D14: 12000 | E14: =SUMIFS('Manual Expense Entry'!D$8:D$100, 'Manual Expense Entry'!C$8:C$100, A14) | F14: =D14-E14 | G14: Municipal taxes, safety certifications, annual company registration, ISO quality compliance
A15: Professional Services | B15: External Consulting | C15: Discretionary / Retainer | D15: 8000 | E15: =SUMIFS('Manual Expense Entry'!D$8:D$100, 'Manual Expense Entry'!C$8:C$100, A15) | F15: =D15-E15 | G15: External corporate counsel retainers, CPA audit fees, specialized tax & IT consulting
A16: Depreciation | B16: Non-Cash Expense | C16: Fixed (Scheduled) | D16: 5000 | E16: =SUMIFS('Manual Expense Entry'!D$8:D$100, 'Manual Expense Entry'!C$8:C$100, A16) | F16: =D16-E16 | G16: Scheduled straight-line depreciation of office furniture, diagnostic computers, showroom gear
A17: Miscellaneous / Other | B17: Sundry Expenses | C17: Discretionary | D17: 4000 | E17: =SUMIFS('Manual Expense Entry'!D$8:D$100, 'Manual Expense Entry'!C$8:C$100, A17) | F17: =D17-E17 | G17: Incidental office supplies, employee hospitality, technical periodicals, emergency petty cash
A18: Custom / Project-Specific | B18: User Defined | C18: Variable | D18: 10000 | E18: =SUMIFS('Manual Expense Entry'!D$8:D$100, 'Manual Expense Entry'!C$8:C$100, A18) | F18: =D18-E18 | G18: User-customizable category for specialized project contingencies or certification programs
A19: TOTAL BUDGET & ACTUALS | B19: - | C19: - | D19: =SUM(D8:D18) | E19: =SUM(E8:E18) | F19: =SUM(F8:F18) | G19: Budget vs Actual Variance Summary

Sheet Visuals & Waterfall
A1: PROFIT BRIDGE & EXPENSE IMPACT VISUALS
A2: Graphical presentation of Gross Profit erosion through operating expense categories into final Net Profit.
A5: Bridge Step | B5: Amount ($) | D5: Expense Category | E5: Total Spend ($)
A6: Gross Revenue | B6: ='P&L & Profit Integration'!B12 | D6: Operating Costs | E6: ='Category Setup & Legend'!E8
A7: Less: Direct COGS | B7: =-'P&L & Profit Integration'!B13 | D7: Salaries & Wages | E7: ='Category Setup & Legend'!E9
A8: Less: Direct Labor | B8: =-'P&L & Profit Integration'!B14 | D8: Utilities & Facilities | E8: ='Category Setup & Legend'!E10
A9: GROSS PROFIT | B9: ='P&L & Profit Integration'!B15 | D9: Marketing & Advertising | E9: ='Category Setup & Legend'!E11
A10: Less: Operating Costs | B10: =-'P&L & Profit Integration'!B19 | D10: Equipment & Maintenance | E10: ='Category Setup & Legend'!E12
A11: Less: Salaries & Wages | B11: =-'P&L & Profit Integration'!B20 | D11: Shipping & Logistics | E11: ='Category Setup & Legend'!E13
A12: Less: Utilities & Facilities | B12: =-'P&L & Profit Integration'!B21 | D12: Taxes & Compliance | E12: ='Category Setup & Legend'!E14
A13: Less: Marketing & Ads | B13: =-'P&L & Profit Integration'!B22 | D13: Professional Services | E13: ='Category Setup & Legend'!E15
A14: Less: Equip & Maintenance | B14: =-'P&L & Profit Integration'!B23 | D14: Depreciation | E14: ='Category Setup & Legend'!E16
A15: Less: Shipping & Logistics | B15: =-'P&L & Profit Integration'!B24 | D15: Miscellaneous / Other | E15: ='Category Setup & Legend'!E17
A16: Less: Taxes & Compliance | B16: =-'P&L & Profit Integration'!B25 | D16: Custom / Project-Specific | E16: ='Category Setup & Legend'!E18
A17: Less: Professional Services | B17: =-'P&L & Profit Integration'!B26
A18: Less: Depreciation | B18: =-'P&L & Profit Integration'!B27
A19: Less: Misc & Custom | B19: =-'P&L & Profit Integration'!B28
A20: NET OPERATING PROFIT | B20: ='P&L & Profit Integration'!B30

Sheet Audit & Documentation
A1: EQUATION REVIEW, AUDIT VERIFICATION & USER MANUAL
A2: Complete mathematical proofs, order of operations, circular reference certification, and user instructions.
A5: 1. MATHEMATICAL FORMULA AUDIT MATRIX
A6: Metric / Calculation | B6: Excel Formula Implementation | C6: Mathematical Formulation | D6: Dependencies | E6: Audit Status | F6: Verification Notes
A7: Gross Revenue | B7: =B12 (P&L Sheet) | C7: R = Sum(Invoiced Quotations) | D7: Sales Ledger | E7: VERIFIED [OK] | F7: Direct sum from confirmed billed accounts
A8: Direct COGS & Labor | B8: =B13, B14 (P&L Sheet) | C8: COGS = Parts + Direct Labor | D8: Procurement & Field Log | E8: VERIFIED [OK] | F8: Includes materials, direct subcontracting
A9: Gross Profit | B9: =B12 - B13 - B14 | C9: GP = R - (COGS + DL) | D9: Revenue, Direct Costs | E9: VERIFIED [OK] | F9: Order of operations: R - COGS - DL
A10: Gross Margin % | B10: =B15 / B12 | C10: GM% = GP / R | D10: Gross Profit, Revenue | E10: VERIFIED [OK] | F10: Formatted as 0.0% with divide-by-zero safety
A11: Manual Expense Sum | B11: =SUM(D8:D100) (Ledger) | C11: Total_OpEx = Sum(i=1..N, Amount_i) | D11: Manual Expense Ledger | E11: VERIFIED [OK] | F11: Dynamically captures up to 100 entries
A12: Category Spend | B12: =SUMIFS(D$8:D$100, C$8:C$100, Cat) | C12: Spend_k = Sum(Amount | Category=k) | D12: Ledger Amount, Category | E12: VERIFIED [OK] | F12: Exact string matching with Setup categories
A13: Running Ledger Total | B13: =SUM(D$8:D8) (Row-by-row) | C13: RT_n = Sum(i=1..n, Amount_i) | D13: Amount Column | E13: VERIFIED [OK] | F13: Cumulative sum anchored at first row D$8
A14: Net Operating Profit | B14: =B15 - B18 | C14: NOP = GP - Total_OpEx | D14: Gross Profit, Total OpEx | E14: VERIFIED [OK] | F14: Automatic deduction of all manual expenses
A15: Net Profit Margin % | B15: =B30 / B12 | C15: NM% = NOP / R | D15: Net Profit, Revenue | E15: VERIFIED [OK] | F15: Benchmarked against 20-25% corporate threshold
A16: Budget Variance | B16: =D_Budget - E_Actual | C16: Var_k = Budget_k - Spend_k | D16: Budget Target, Actual | E16: VERIFIED [OK] | F16: Positive = Favorable, Negative = Overbudget
A19: 2. OPERATING INSTRUCTIONS & WORKFLOW GUIDE
A20: Step 1: Adding New Expenses | B20: Navigate to the 'Manual Expense Entry' tab. In the first available empty row, enter Date (YYYY-MM-DD), select an approved category from the dropdown in Column C, enter the Amount ($), and input Vendor and Business Notes.
A21: Step 2: Monitoring Running Totals | B21: The 'Running Total ($)' in Column E updates automatically row-by-row. The summary header in Cell F4 shows the instantaneous grand total of all manual operating costs.
A22: Step 3: Managing Custom Categories | B22: To introduce custom cost categories, open the 'Category Setup & Legend' tab and define the new category name in Column A (rows 8-18). The Data Validation dropdown in the ledger will immediately reflect new options.
A23: Step 4: Reviewing Profit Deduction | B23: Switch to 'P&L & Profit Integration'. Cell B18 automatically aggregates all manual expenses via live formula link. Net Operating Profit (Cell B30 = Gross Profit - Total Expenses) recalculates instantaneously without manual intervention.
A24: Step 5: Visualizing Allocation & Impact | B24: Inspect 'Visuals & Waterfall' to review the step-by-step profit bridge, category distribution bar chart, and expense percentage allocation pie chart.
A27: 3. MODEL ASSUMPTIONS & INTEGRITY CERTIFICATION
A28: Order of Operations Integrity | B28: All calculations follow strict GAAP hierarchy: Gross Revenue -> Less Direct Costs = Gross Profit -> Less Operating Expenses = Net Operating Profit (EBIT). No intermediate tax distortions.
A29: Zero Circular References | B29: All formulas strictly flow downstream: Manual Entries -> Category Subtotals -> P&L Summary -> KPIs & Visuals. Verified 100% acyclic dependency graph.
A30: Consistency of Currency & Units | B30: All currency cells are formatted to standard 2-decimal accounting format ($#,##0.00). Percentages are formatted to 1-decimal precision (0.0%).
A31: Accrual vs Cash Timing | B31: Manual expenses are recognized in the period logged by Date. Recurring scheduled items (e.g. depreciation) reflect standard monthly allocation schedules.
